{"cameraMode":{"drawMode":0,"name":"Shaded","section":"Shading Mode"},"sceneLighting":true,"audioPlay":false,"sceneViewState":{"showFog":true,"showMaterialUpdate":false,"showSkybox":true,"showFlares":true,"showImageEffects":true,"showParticleSystems":true},"in2DMode":false,"pivot":{"x":-24.07234001159668,"y":-0.13466176390647889,"z":1.7869858741760255},"rotation":{"x":0.046933501958847049,"y":0.6258757710456848,"z":-0.03781506419181824,"w":0.7775904536247253},"size":1.0496070384979249,"orthographic":false}